google_translator_simplified/__init__.py
google_translator_simplified/translator_complex.py
google_translator_simplified/translator_constant.py
google_translator_simplified/translator_simplified.py
google_translator_simplified-0.0.7.dist-info/METADATA
google_translator_simplified-0.0.7.dist-info/WHEEL
google_translator_simplified-0.0.7.dist-info/top_level.txt
google_translator_simplified-0.0.7.dist-info/RECORD
