Metadata-Version: 2.1
Name: google-translator-simplified
Version: 0.0.7
Summary: Class for translating texts and detecting language (based on Google Translator).
Home-page: https://github.com/ksproska/google_translator_simplified
Author: Kamila Sproska
Author-email: kamila.sproska@gmail.com
License: UNKNOWN
Keywords: python,google,translator,simple,google translator
Platform: UNKNOWN
